switchport/__init__.py
switchport/client.py
switchport/exceptions.py
switchport/metrics.py
switchport/prompts.py
switchport/types.py
switchport-0.4.1.dist-info/METADATA
switchport-0.4.1.dist-info/WHEEL
switchport-0.4.1.dist-info/licenses/LICENSE
switchport-0.4.1.dist-info/RECORD
