Metadata-Version: 2.4
Name: switchport
Version: 0.4.1
Summary: Python SDK for Switchport - Prompt management and A/B testing platform
Project-URL: Homepage, https://switchport.ai
Project-URL: Documentation, https://docs.switchport.ai/sdk/python/quickstart
Project-URL: Repository, https://github.com/switchport-ai/switchport-python
Project-URL: Issues, https://github.com/switchport-ai/switchport-python/issues
Author-email: Switchport <hello@switchport.ai>
License: MIT
License-File: LICENSE
Keywords: a/b testing,ai,llm,prompt,sdk,switchport
Classifier: Development Status :: 3 - Alpha
Classifier: Intended Audience :: Developers
Classifier: License :: OSI Approved :: MIT License
Classifier: Operating System :: OS Independent
Classifier: Programming Language :: Python :: 3
Classifier: Programming Language :: Python :: 3.8
Classifier: Programming Language :: Python :: 3.9
Classifier: Programming Language :: Python :: 3.10
Classifier: Programming Language :: Python :: 3.11
Classifier: Programming Language :: Python :: 3.12
Classifier: Topic :: Software Development :: Libraries :: Python Modules
Requires-Python: >=3.8
Requires-Dist: pydantic>=2.0.0
Requires-Dist: python-dotenv>=1.0.0
Requires-Dist: requests>=2.31.0
Provides-Extra: dev
Requires-Dist: black>=23.0.0; extra == 'dev'
Requires-Dist: mypy>=1.0.0; extra == 'dev'
Requires-Dist: pytest-cov>=4.0.0; extra == 'dev'
Requires-Dist: pytest>=7.0.0; extra == 'dev'
